[
    {
        "id": 1001,
        "first_name": "Corbin",
        "last_name": "Hauck",
        "holding": 151967,
        "location": {
            "country": "SE",
            "address": "Brunnsgatan 7"
        }
    },
    {
        "id": 1002,
        "first_name": "Vanya",
        "last_name": "Worsell",
        "holding": 2151967,
        "location": {
            "country": "US",
            "address": "Asteroid road 5"
        }
    },
    {
        "id": 1003,
        "first_name": "Eldon",
        "last_name": "McCartan",
        "holding": 2351967,
        "location": {
            "country": "SE",
            "address": "Vimmerbygatan 20"
        }
    },
    {
        "id": 1004,
        "first_name": "Ingunna",
        "last_name": "Castellucci",
        "holding": 4151967,
        "location": {
            "country": "US",
            "address": "Comet road 41"
        }
    }
]